streamlit_text_label/__init__.py
streamlit_text_label/frontend/build/asset-manifest.json
streamlit_text_label/frontend/build/bootstrap.min.css
streamlit_text_label/frontend/build/custom.css
streamlit_text_label/frontend/build/index.html
streamlit_text_label/frontend/build/static/css/2.d4928237.chunk.css
streamlit_text_label/frontend/build/static/css/2.d4928237.chunk.css.map
streamlit_text_label/frontend/build/static/js/2.f98235b8.chunk.js
streamlit_text_label/frontend/build/static/js/2.f98235b8.chunk.js.LICENSE.txt
streamlit_text_label/frontend/build/static/js/2.f98235b8.chunk.js.map
streamlit_text_label/frontend/build/static/js/main.891d6351.chunk.js
streamlit_text_label/frontend/build/static/js/main.891d6351.chunk.js.map
streamlit_text_label/frontend/build/static/js/runtime-main.6d98f643.js
streamlit_text_label/frontend/build/static/js/runtime-main.6d98f643.js.map
streamlit_text_label-0.1.2.dist-info/LICENSE
streamlit_text_label-0.1.2.dist-info/METADATA
streamlit_text_label-0.1.2.dist-info/WHEEL
streamlit_text_label-0.1.2.dist-info/top_level.txt
streamlit_text_label-0.1.2.dist-info/RECORD
