Metadata-Version: 2.1
Name: streamlit-text-label
Version: 0.1.2
Summary: Components for labelling text document
Home-page: https://github.com/sweatybridge/streamlit-text-label
Author: Han Qiao
Author-email: sweatybridge@gmail.com
Classifier: Programming Language :: Python :: 3
Classifier: Programming Language :: Python :: 3.7
Classifier: Programming Language :: Python :: 3.8
Classifier: Programming Language :: Python :: 3.9
Classifier: Programming Language :: Python :: 3.10
Classifier: License :: OSI Approved :: Apache Software License
Classifier: Operating System :: OS Independent
Requires-Python: >=3.7
License-File: LICENSE
Requires-Dist: streamlit (>=0.63)
